[
    {
        "titulo": "Regular orders for triangular fuzzy numbers and the weak law of trichotomy",
        "data_publicacao": "2026-06-01",
        "autores": [
            {
                "nome": "Santos J.C.d.",
                "afiliacoes": [
                    "Universidade Federal Rural de Pernambuco"
                ]
            }
        ],
        "doi": "10.1016/j.fss.2026.109790"
    },
    {
        "titulo": "The Influence of Cascade Dams on Multifractality of River Flow",
        "data_publicacao": "2026-03-01",
        "autores": [
            {
                "nome": "Stosic T.",
                "afiliacoes": [
                    "Universidade Federal Rural de Pernambuco"
                ]
            },
            {
                "nome": "Singh V.P.",
                "afiliacoes": [
                    "Department of Biological and Agricultural Engineering"
                ]
            },
            {
                "nome": "Stosic B.",
                "afiliacoes": [
                    "Universidade Federal Rural de Pernambuco"
                ]
            }
        ],
        "doi": "10.3390/su18052276"
    },
    {
        "titulo": "S-iNAS: A Performance-Centric SRN Modeling and Analysis of Time and Event Based Scaling Strategies in Ceph-Based Industrial Network-Attached Storage",
        "data_publicacao": "2026-03-01",
        "autores": [
            {
                "nome": "Lim D.",
                "afiliacoes": [
                    "Konkuk University"
                ]
            },
            {
                "nome": "Nguyen T.A.",
                "afiliacoes": [
                    "Ho Chi Minh City University of Industry and Trade"
                ]
            },
            {
                "nome": "Li J.",
                "afiliacoes": [
                    "Konkuk University"
                ]
            },
            {
                "nome": "Choi E.",
                "afiliacoes": [
                    "Kookmin University"
                ]
            },
            {
                "nome": "Min D.",
                "afiliacoes": [
                    "Konkuk University",
                    "Konkuk University"
                ]
            },
            {
                "nome": "Cadena R.M.",
                "afiliacoes": [
                    "Polytechnic University of Victoria"
                ]
            },
            {
                "nome": "Nogueira B.",
                "afiliacoes": [
                    "Universidade Federal de Pernambuco"
                ]
            },
            {
                "nome": "Andrade E.",
                "afiliacoes": [
                    "Universidade Federal Rural de Pernambuco"
                ]
            },
            {
                "nome": "Callou G.",
                "afiliacoes": [
                    "Universidade Federal Rural de Pernambuco"
                ]
            },
            {
                "nome": "Di Mauro M.",
                "afiliacoes": [
                    "Università degli Studi di Salerno"
                ]
            },
            {
                "nome": "Torquato M.",
                "afiliacoes": [
                    "University of Coimbra, Centre for Informatics and System",
                    "Universidade Federal de Alagoas"
                ]
            },
            {
                "nome": "Silva F.A.",
                "afiliacoes": [
                    "Universidade Federal do Piauí"
                ]
            },
            {
                "nome": "Maciel P.",
                "afiliacoes": [
                    "Universidade Federal de Pernambuco"
                ]
            }
        ],
        "doi": "10.1007/s10922-025-10005-6"
    },
    {
        "titulo": "Correction: Challenges and Opportunities for New Frontiers and Technologies to Guarantee Food Production (Sustainability, (2025), 17, 9, (3792), 10.3390/su17093792)",
        "data_publicacao": "2026-02-01",
        "autores": [
            {
                "nome": "Silva J.C.F.",
                "afiliacoes": [
                    "The Thought for Food® Foundation",
                    "University of Florida Institute of Food and Agricultural Sciences"
                ]
            },
            {
                "nome": "Machado K.L.d.G.",
                "afiliacoes": [
                    "The Thought for Food® Foundation",
                    "Universidade Federal de Vicosa"
                ]
            },
            {
                "nome": "Silva A.F.d.S.",
                "afiliacoes": [
                    "The Thought for Food® Foundation",
                    "Van Hall-Larenstein University of Applied Sciences",
                    "University of Applied Sciences van Hall"
                ]
            },
            {
                "nome": "Dias R.",
                "afiliacoes": [
                    "University of Florida Institute of Food and Agricultural Sciences"
                ]
            },
            {
                "nome": "Bodnar V.R.",
                "afiliacoes": [
                    "The Thought for Food® Foundation"
                ]
            },
            {
                "nome": "Vieira W.O.",
                "afiliacoes": [
                    "The Thought for Food® Foundation",
                    "Bioworld Soluções Regenerativas",
                    "Universidade Federal Rural de Pernambuco"
                ]
            },
            {
                "nome": "Moreno-Pizani M.A.",
                "afiliacoes": [
                    "The Thought for Food® Foundation",
                    "Instituto de Pesquisas e Educação Continuada em Economia e Gestão de Empresas (PECEGE)"
                ]
            },
            {
                "nome": "Ramos J.D.",
                "afiliacoes": [
                    "The Thought for Food® Foundation",
                    "Empresa Brasileira de Pesquisa Agropecuária - Embrapa"
                ]
            },
            {
                "nome": "Pauli I.",
                "afiliacoes": [
                    "The Thought for Food® Foundation"
                ]
            },
            {
                "nome": "Costa L.C.d.",
                "afiliacoes": [
                    "The Thought for Food® Foundation",
                    "Universidade Federal Rural da Amazonia"
                ]
            }
        ],
        "doi": "10.3390/su18041866"
    },
    {
        "titulo": "Selecting Consensus Algorithm Integrations in a DAG-based Blockchain for IoT Using Genetic Algorithms",
        "data_publicacao": "2026-01-09",
        "autores": [
            {
                "nome": "de Morais A.M.",
                "afiliacoes": [
                    "Universidade Federal de Pernambuco"
                ]
            },
            {
                "nome": "Lins F.A.A.",
                "afiliacoes": [
                    "Universidade Federal Rural de Pernambuco"
                ]
            },
            {
                "nome": "Rosa N.S.",
                "afiliacoes": [
                    "Universidade Federal de Pernambuco"
                ]
            }
        ],
        "doi": "10.5753/jisa.2026.5926"
    },
    {
        "titulo": "Impact of Image Resolution on Drone Surveillance System Availability: A Stochastic Petri Net Approach",
        "data_publicacao": "2026-01-01",
        "autores": [
            {
                "nome": "Borges I.",
                "afiliacoes": [
                    "Universidade Federal de Pernambuco"
                ]
            },
            {
                "nome": "Lins L.",
                "afiliacoes": [
                    "Universidade Federal de Pernambuco"
                ]
            },
            {
                "nome": "Callou G.",
                "afiliacoes": [
                    "Universidade Federal Rural de Pernambuco"
                ]
            },
            {
                "nome": "Maciel P.",
                "afiliacoes": [
                    "Universidade Federal de Pernambuco"
                ]
            }
        ],
        "doi": "10.1007/978-3-032-11539-3_16"
    },
    {
        "titulo": "Neural Networks with Adaptive and Trainable Activation Functions Applied to Solve Stochastic Differential Equations",
        "data_publicacao": "2026-01-01",
        "autores": [
            {
                "nome": "Felix I.d.A.",
                "afiliacoes": [
                    "Universidade Federal Rural de Pernambuco"
                ]
            },
            {
                "nome": "Delgado J.H.d.M.",
                "afiliacoes": [
                    "Universidade Federal Rural de Pernambuco"
                ]
            },
            {
                "nome": "Ferreira T.A.E.",
                "afiliacoes": [
                    "Universidade Federal Rural de Pernambuco"
                ]
            }
        ],
        "doi": "10.1007/978-3-032-15984-7_15"
    },
    {
        "titulo": "Increasing Time Series Forecasting Performance with Dynamic System Copula-Based Ensemble Models",
        "data_publicacao": "2026-01-01",
        "autores": [
            {
                "nome": "Neto A.",
                "afiliacoes": [
                    "Universidade Federal do Cariri - UFCA"
                ]
            },
            {
                "nome": "Ferreira T.",
                "afiliacoes": [
                    "Universidade Federal Rural de Pernambuco"
                ]
            },
            {
                "nome": "Firmino P.",
                "afiliacoes": [
                    "Universidade Federal do Cariri - UFCA"
                ]
            }
        ],
        "doi": "10.1007/978-3-032-15984-7_5"
    },
    {
        "titulo": "A Comprehensive Study of Fitness Landscapes in AutoML: The Impact of Dataset Complexity and Search Space Neutrality",
        "data_publicacao": "2026-01-01",
        "autores": [
            {
                "nome": "França T.R.",
                "afiliacoes": [
                    "Universidade Federal de Pernambuco"
                ]
            },
            {
                "nome": "Prudêncio R.B.C.",
                "afiliacoes": [
                    "Universidade Federal de Pernambuco"
                ]
            },
            {
                "nome": "de Miranda P.B.C.",
                "afiliacoes": [
                    "Universidade Federal Rural de Pernambuco"
                ]
            }
        ],
        "doi": "10.1007/978-3-032-15987-8_2"
    },
    {
        "titulo": "The Turner 2-Strings Machines",
        "data_publicacao": "2026-01-01",
        "autores": [
            {
                "nome": "Lins R.D.",
                "afiliacoes": [
                    "Universidade Federal Rural de Pernambuco",
                    "Universidade Federal de Pernambuco"
                ]
            }
        ],
        "doi": "10.1007/978-3-032-12086-1_12"
    },
    {
        "titulo": "A Research Agenda for the Living SysML V2 Blueprint: Toward Executable, Verifiable, and Navigable System Models",
        "data_publicacao": "2026-01-01",
        "autores": [
            {
                "nome": "Teodorov C.",
                "afiliacoes": [
                    "Institut Polytechnique de Paris",
                    "Laboratoire des Sciences et Techniques de l'Information, de la Communication et de la Connaissance (Lab-Sticc)"
                ]
            },
            {
                "nome": "Lima L.",
                "afiliacoes": [
                    "Universidade Federal Rural de Pernambuco"
                ]
            },
            {
                "nome": "Nogueira S.C.",
                "afiliacoes": [
                    "Universidade Federal Rural de Pernambuco"
                ]
            },
            {
                "nome": "Guerin S.",
                "afiliacoes": [
                    "IMT Atlantique",
                    "Laboratoire des Sciences et Techniques de l'Information, de la Communication et de la Connaissance (Lab-Sticc)"
                ]
            },
            {
                "nome": "Lagadec L.",
                "afiliacoes": [
                    "Institut Polytechnique de Paris",
                    "Laboratoire des Sciences et Techniques de l'Information, de la Communication et de la Connaissance (Lab-Sticc)"
                ]
            }
        ],
        "doi": "10.1007/978-3-032-12086-1_4"
    },
    {
        "titulo": "Tutoria: Delivering Personalized Feedback at Scale with Artificial Intelligence",
        "data_publicacao": "2026-01-01",
        "autores": [
            {
                "nome": "da Costa N.T.",
                "afiliacoes": [
                    "Instituto Federal Goiano – IF Goiano",
                    "CESAR Centro de Estudios e Sistemas Avancados do Recife"
                ]
            },
            {
                "nome": "Xavier C.",
                "afiliacoes": [
                    "Instituto Federal Goiano – IF Goiano"
                ]
            },
            {
                "nome": "Ribeiro F.G.C.",
                "afiliacoes": [
                    "Universidade Tecnológica Federal do Paraná"
                ]
            },
            {
                "nome": "Júnior G.A.d.A.",
                "afiliacoes": [
                    "Universidade Federal de Pernambuco"
                ]
            },
            {
                "nome": "Rodrigues L.",
                "afiliacoes": [
                    "Universidade Tecnológica Federal do Paraná",
                    "CESAR Centro de Estudios e Sistemas Avancados do Recife"
                ]
            },
            {
                "nome": "Falcão T.P.d.R.",
                "afiliacoes": [
                    "Universidade Federal de Pernambuco"
                ]
            },
            {
                "nome": "Mello R.F.",
                "afiliacoes": [
                    "Universidade Federal de Pernambuco",
                    "CESAR Centro de Estudios e Sistemas Avancados do Recife"
                ]
            }
        ],
        "doi": "10.1007/978-3-032-03873-9_54"
    },
    {
        "titulo": "SIMBA: A Tool for Designing Generative AI Agents for Reflective Learning and Critical Thinking",
        "data_publicacao": "2026-01-01",
        "autores": [
            {
                "nome": "Ferrettini G.",
                "afiliacoes": [
                    "Université de Toulouse"
                ]
            },
            {
                "nome": "Nascimento A.C.A.",
                "afiliacoes": [
                    "Universidade Federal Rural de Pernambuco"
                ]
            },
            {
                "nome": "Pérez-Sanagustin M.",
                "afiliacoes": [
                    "Université de Toulouse"
                ]
            },
            {
                "nome": "Hilliger I.",
                "afiliacoes": [
                    "Pontificia Universidad Católica de Chile"
                ]
            }
        ],
        "doi": "10.1007/978-3-032-03873-9_42"
    },
    {
        "titulo": "Preface",
        "data_publicacao": "2026-01-01",
        "autores": [
            {
                "nome": "Tammets K.",
                "afiliacoes": [
                    "Tallinn University"
                ]
            },
            {
                "nome": "Sosnovsky S.",
                "afiliacoes": [
                    "Universiteit Utrecht"
                ]
            },
            {
                "nome": "Ferreira Mello R.",
                "afiliacoes": [
                    "Universidade Federal Rural de Pernambuco"
                ]
            },
            {
                "nome": "Nazaretsky T.",
                "afiliacoes": [
                    "École Polytechnique Fédérale de Lausanne"
                ]
            },
            {
                "nome": "Pishtari G.",
                "afiliacoes": [
                    "University for Continuing Education Krems"
                ]
            }
        ],
        "doi": null
    },
    {
        "titulo": "Improving power consumption in IoT devices through neural network-based decision making",
        "data_publicacao": "2026-01-01",
        "autores": [
            {
                "nome": "Da Silva V.G.",
                "afiliacoes": [
                    "Universidade Federal de Pernambuco"
                ]
            },
            {
                "nome": "Rosa N.S.",
                "afiliacoes": [
                    "Universidade Federal de Pernambuco"
                ]
            },
            {
                "nome": "Aires F.",
                "afiliacoes": [
                    "Universidade Federal Rural de Pernambuco"
                ]
            },
            {
                "nome": "Santos W.R.M.",
                "afiliacoes": [
                    "CESAR Centro de Estudios e Sistemas Avancados do Recife"
                ]
            }
        ],
        "doi": "10.1016/j.iot.2025.101827"
    },
    {
        "titulo": "From Diverse Origins to a DEI Crisis: The Pushback Against Equity, Diversity, and Inclusion in Software Engineering",
        "data_publicacao": "2026-01-01",
        "autores": [
            {
                "nome": "de Souza Santos R.",
                "afiliacoes": [
                    "University of Calgary"
                ]
            },
            {
                "nome": "Magalhaes C.",
                "afiliacoes": [
                    "Universidade Federal Rural de Pernambuco"
                ]
            },
            {
                "nome": "Barcomb A.",
                "afiliacoes": [
                    "University of Calgary"
                ]
            },
            {
                "nome": "Wessel M.",
                "afiliacoes": [
                    "Radboud Universiteit"
                ]
            }
        ],
        "doi": "10.1007/978-3-032-04207-1_12"
    },
    {
        "titulo": "Ethical Design and Child Protection in Platformized Education",
        "data_publicacao": "2026-01-01",
        "autores": [
            {
                "nome": "Valença G.",
                "afiliacoes": [
                    "Universidade Federal Rural de Pernambuco"
                ]
            },
            {
                "nome": "Nejm R.",
                "afiliacoes": [
                    "Instituto Alana"
                ]
            },
            {
                "nome": "Mello M.",
                "afiliacoes": [
                    "Instituto Alana"
                ]
            },
            {
                "nome": "Mendonça J.",
                "afiliacoes": [
                    "Instituto Alana"
                ]
            },
            {
                "nome": "Vasconcelos F.",
                "afiliacoes": [
                    "Instituto Dimicuida"
                ]
            },
            {
                "nome": "Mendonça H.",
                "afiliacoes": [
                    "Bioma Educação"
                ]
            }
        ],
        "doi": "10.1007/978-3-032-05008-3_29"
    },
    {
        "titulo": "Preface",
        "data_publicacao": "2026-01-01",
        "autores": [
            {
                "nome": "Tammets K.",
                "afiliacoes": [
                    "Tallinn University"
                ]
            },
            {
                "nome": "Sosnovsky S.",
                "afiliacoes": [
                    "Universiteit Utrecht"
                ]
            },
            {
                "nome": "Mello R.F.",
                "afiliacoes": [
                    "Universidade Federal Rural de Pernambuco"
                ]
            },
            {
                "nome": "Nazaretsky T.",
                "afiliacoes": [
                    "École Polytechnique Fédérale de Lausanne"
                ]
            },
            {
                "nome": "Pishtari G.",
                "afiliacoes": [
                    "University for Continuing Education Krems"
                ]
            }
        ],
        "doi": null
    }
]